lorator/__init__.py
lorator/commands/__init__.py
lorator/commands/application.py
lorator/commands/command.py
lorator/commands/migrations/__init__.py
lorator/commands/migrations/base_command.py
lorator/commands/migrations/install_command.py
lorator/commands/migrations/make_command.py
lorator/commands/migrations/migrate_command.py
lorator/commands/migrations/refresh_command.py
lorator/commands/migrations/reset_command.py
lorator/commands/migrations/rollback_command.py
lorator/commands/migrations/status_command.py
lorator/commands/models/__init__.py
lorator/commands/models/make_command.py
lorator/commands/models/stubs.py
lorator/commands/seeds/__init__.py
lorator/commands/seeds/base_command.py
lorator/commands/seeds/make_command.py
lorator/commands/seeds/seed_command.py
lorator/connections/__init__.py
lorator/connections/connection.py
lorator/connections/connection_interface.py
lorator/connections/connection_resolver_interface.py
lorator/connections/empty_connection.py
lorator/connections/mysql_connection.py
lorator/connections/postgres_connection.py
lorator/connections/rds_postgres_connection.py
lorator/connections/sqlite_connection.py
lorator/connectors/__init__.py
lorator/connectors/connection_factory.py
lorator/connectors/connector.py
lorator/connectors/empty_connector.py
lorator/connectors/mysql_connector.py
lorator/connectors/postgres_connector.py
lorator/connectors/rds_postgres_connector.py
lorator/connectors/sqlite_connector.py
lorator/database_manager.py
lorator/dbal/__init__.py
lorator/dbal/abstract_asset.py
lorator/dbal/column.py
lorator/dbal/column_diff.py
lorator/dbal/comparator.py
lorator/dbal/exceptions/__init__.py
lorator/dbal/foreign_key_constraint.py
lorator/dbal/identifier.py
lorator/dbal/index.py
lorator/dbal/mysql_schema_manager.py
lorator/dbal/platforms/__init__.py
lorator/dbal/platforms/keywords/__init__.py
lorator/dbal/platforms/keywords/keyword_list.py
lorator/dbal/platforms/keywords/mysql_keywords.py
lorator-0.9.9.2.dist-info/entry_points.txt
lorator-0.9.9.2.dist-info/LICENSE
lorator-0.9.9.2.dist-info/WHEEL
lorator-0.9.9.2.dist-info/METADATA
lorator-0.9.9.2.dist-info/RECORD
